{"version":1,"resource":"file:///home/baia-13/Documentos/Botanica-jardim/statics/templates/index.ejs","entries":[{"id":"SMbK.ejs","timestamp":1702040907683},{"id":"FOdq.ejs","timestamp":1702041052738},{"id":"Pwdx.ejs","source":"undoRedo.source","timestamp":1702041077938},{"id":"MIqo.ejs","timestamp":1702041290156},{"id":"0Ysa.ejs","source":"undoRedo.source","timestamp":1702041297740},{"id":"z458.ejs","timestamp":1702041642810},{"id":"AEwq.ejs","timestamp":1702041657274},{"id":"5n94.ejs","timestamp":1702041671465},{"id":"89dp.ejs","timestamp":1702042084926},{"id":"AQcx.ejs","timestamp":1702042259353},{"id":"FMwK.ejs","timestamp":1702042348928},{"id":"Z7xe.ejs","timestamp":1702042378536},{"id":"Hzwa.ejs","timestamp":1702042389312},{"id":"Wesn.ejs","timestamp":1702042608762},{"id":"z3IL.ejs","timestamp":1702042657726},{"id":"cbQI.ejs","timestamp":1702042669966},{"id":"ApFM.ejs","timestamp":1702042693406},{"id":"k5v9.ejs","timestamp":1702042724694},{"id":"C3aI.ejs","timestamp":1702042772425},{"id":"rITL.ejs","timestamp":1702042820873},{"id":"hYNJ.ejs","timestamp":1702042843609},{"id":"5vEC.ejs","timestamp":1702044339338},{"id":"CCCq.ejs","timestamp":1702044695275},{"id":"AWcS.ejs","timestamp":1702045269427},{"id":"Irfl.ejs","timestamp":1702045319959},{"id":"XTJg.ejs","timestamp":1702045330619},{"id":"MJ84.ejs","timestamp":1702045526701},{"id":"90nE.ejs","timestamp":1702045546741},{"id":"62a4.ejs","timestamp":1702045586445},{"id":"ujL9.ejs","timestamp":1702045603629},{"id":"y5Fm.ejs","timestamp":1702045617297},{"id":"BMNT.ejs","source":"undoRedo.source","timestamp":1702045629173},{"id":"OyEE.ejs","timestamp":1702047296145},{"id":"zUlv.ejs","source":"undoRedo.source","timestamp":1702047303665},{"id":"DPCM.ejs","timestamp":1702047679798},{"id":"5Br0.ejs","timestamp":1702048551968},{"id":"nn8p.ejs","timestamp":1702048837174},{"id":"II95.ejs","timestamp":1702055700590},{"id":"jZqb.ejs","timestamp":1702056269186},{"id":"3B5H.ejs","timestamp":1702056291657},{"id":"onTs.ejs","timestamp":1702057650744},{"id":"NMgx.ejs","timestamp":1702057674256},{"id":"Nwvj.ejs","timestamp":1702057690000}]}